BigNumber.py
Factorize.py
Prime.py
pyecm.py
Prime/Prime.py
Hypermath-0.0.2.dist-info/METADATA
Hypermath-0.0.2.dist-info/WHEEL
Hypermath-0.0.2.dist-info/top_level.txt
Hypermath-0.0.2.dist-info/RECORD
